terracost/__init__.py
terracost/main.py
terracost/services/__init__.py
terracost/services/aws_cost_service.py
terracost/services/azure_cost_service.py
terracost/services/base_cost_service.py
terracost/services/cicd_service.py
terracost/services/gcp_cost_service.py
terracost/services/progress_indicator.py
terracost/services/suggest_progress.py
terracost/services/suggest_service.py
terracost/services/terraform_file_parser.py
terracost-0.1.1.dist-info/licenses/LICENSE
terracost-0.1.1.dist-info/METADATA
terracost-0.1.1.dist-info/WHEEL
terracost-0.1.1.dist-info/entry_points.txt
terracost-0.1.1.dist-info/top_level.txt
terracost-0.1.1.dist-info/RECORD
