Metadata-Version: 2.4
Name: terracost
Version: 0.1.1
Summary: A tool for estimating Terraform infrastructure costs with uncertainty analysis
Home-page: https://github.com/yourusername/terracost
Author: Daniël van Zyl, Shailyn Ramsamy Moodley, Tevlen Naidoo
Author-email: your.email@example.com
License: MIT
Requires-Python: >=3.8
License-File: LICENSE
Requires-Dist: numpy>=1.21.0
Requires-Dist: requests>=2.25.0
Requires-Dist: python-hcl2>=7.0.0
Requires-Dist: pydantic>=2.0.0
Requires-Dist: boto3>=1.26.0
Requires-Dist: langchain>=0.3.0
Requires-Dist: langchain-openai>=0.3.0
Requires-Dist: python-dotenv>=1.0.0
Dynamic: author-email
Dynamic: home-page
Dynamic: license-file
Dynamic: requires-python
